fastairawpy.py
fastai_rawpy-0.0.15.dist-info/License.txt
fastai_rawpy-0.0.15.dist-info/METADATA
fastai_rawpy-0.0.15.dist-info/WHEEL
fastai_rawpy-0.0.15.dist-info/top_level.txt
fastai_rawpy-0.0.15.dist-info/RECORD
