Metadata-Version: 2.1
Name: fastai-rawpy
Version: 0.0.15
Summary: fastai-rawpy connects fast.ai with RawPy, so now fast.ai supports RAW image files
Home-page: https://github.com/lejrn/fastai-RawPy
Author: Tal Leron
Author-email: lrn.tl.dv@gmail.com
License: apache2
Platform: UNKNOWN
Classifier: Programming Language :: Python :: 3.7
Classifier: Programming Language :: Python :: 3.8
Classifier: Programming Language :: Python :: 3.9
Classifier: Programming Language :: Python :: 3.10
Classifier: License :: OSI Approved :: Apache Software License
Requires-Dist: fastai
Requires-Dist: rawpy
Requires-Dist: opencv-python
